thecodecrate_builderable/__init__.py
thecodecrate_builderable/builderable.py
thecodecrate_builderable/builderable_interface.py
thecodecrate_builderable/py.typed
thecodecrate_builderable/types.py
thecodecrate_builderable/partials/with_build_method/builderable_interface_mixin.py
thecodecrate_builderable/partials/with_build_method/builderable_mixin.py
thecodecrate_builderable/partials/with_builderable_base/builderable_interface_mixin.py
thecodecrate_builderable/partials/with_builderable_base/builderable_mixin.py
thecodecrate_builderable/partials/with_list/builderable_interface_mixin.py
thecodecrate_builderable/partials/with_list/builderable_mixin.py
thecodecrate_builderable/traits/has_immutability/has_immutability.py
thecodecrate_builderable/traits/has_immutability/has_immutability_interface.py
thecodecrate_builderable-1.6.0.dist-info/LICENSE
thecodecrate_builderable-1.6.0.dist-info/METADATA
thecodecrate_builderable-1.6.0.dist-info/WHEEL
thecodecrate_builderable-1.6.0.dist-info/top_level.txt
thecodecrate_builderable-1.6.0.dist-info/RECORD
