Metadata-Version: 2.1
Name: thecodecrate-builderable
Version: 1.6.0
Summary: This package provides a builder pattern implementation
Author-email: TheCodeCrate <loureiro.rg@gmail.com>
License: The MIT License (MIT)
Project-URL: repository, https://github.com/thecodecrate/python-builderable
Project-URL: documentation, https://github.com/thecodecrate/python-builderable
Keywords: builder pattern,python,library,python-builderable
Classifier: License :: OSI Approved :: MIT License
Classifier: Programming Language :: Python
Classifier: Programming Language :: Python :: 3
Classifier: Programming Language :: Python :: 3.11
Classifier: Intended Audience :: Developers
Classifier: Topic :: Software Development :: Libraries :: Python Modules
Classifier: Typing :: Typed
Requires-Python: >=3.11
License-File: LICENSE
Provides-Extra: build
Requires-Dist: build; extra == "build"
Requires-Dist: twine; extra == "build"
Provides-Extra: dev
Requires-Dist: black; extra == "dev"
Requires-Dist: bumpver; extra == "dev"
Requires-Dist: isort; extra == "dev"
Requires-Dist: flake8; extra == "dev"
Requires-Dist: pytest; extra == "dev"
Requires-Dist: pytest-cov; extra == "dev"
Requires-Dist: pytest-asyncio; extra == "dev"
